{"RuleTriggered": 0, "Violations": 0, "Details": {"Network": {"algo-1": {"max": 3805.49, "p99": 8.39, "p95": 0, "p50": 0, "min": 0}}, "GPU": {"algo-1": {"max": 89.0, "p99": 86.0, "p95": 73.4, "p50": 0, "min": 0}}, "CPU": {"algo-1": {"max": 100.0, "p99": 91.84, "p95": 85.38, "p50": 41.6, "min": 0}}, "CPU memory": {"algo-1": {"max": 27.85, "p99": 25.9, "p95": 23.85, "p50": 23.33, "min": 7.22}}, "GPU memory": {"algo-1": {"max": 84.0, "p99": 82.0, "p95": 71.0, "p50": 0, "min": 0}}, "I/O": {"algo-1": {"max": 79.26, "p99": 63.03, "p95": 47.97, "p50": 0.5, "min": 0}}}, "Datapoints": 792, "RuleParameters": ""}